.gitignore
Makefile
README.md
pyproject.toml
setup.cfg
setup.py
benchmarks/.gitignore
benchmarks/cigars/.gitignore
benchmarks/cigars/Makefile
benchmarks/cigars/ad_hoc.py
benchmarks/cigars/opstats.py
benchmarks/cigars/textformats_based.py
benchmarks/sam/.gitignore
benchmarks/sam/Makefile
benchmarks/sam/counts.py
benchmarks/sam/htslib_based.py
benchmarks/sam/textformats_based.py
examples/.gitignore
examples/example.oop.py
examples/large_example.py
examples/small_example.py
examples/egc/.gitignore
examples/egc/Makefile
examples/egc/README.md
examples/egc/egc.yaml
examples/egc/egc2json.py
examples/egc/egc2json_ad_hoc.py
examples/egc/egc_ad_hoc.py
examples/egc/example.egc
examples/egc/json2egc.py
examples/egc/json2egc_ad_hoc.py
examples/egc/run_example.sh
examples/ftab_to_gff3/ctg123.ftab
examples/ftab_to_gff3/ftab.yaml
examples/ftab_to_gff3/ftab_to_gff3.py
examples/ftab_to_gff3/run_example.sh
examples/gfa1_fix/.gitignore
examples/gfa1_fix/Makefile
examples/gfa1_fix/complete_graph.gfa
examples/gfa1_fix/gfa1_fix.py
examples/gfa1_fix/gfa1_show_invalid_lines.py
examples/gfa1_fix/invalid_gfa1.yaml
examples/gfa2_info/.gitignore
examples/gfa2_info/Makefile
examples/gfa2_info/download_large_example.sh
examples/gfa2_info/gfa2_cross_validator.py
examples/gfa2_info/gfa2_info.py
examples/gfa2_info/gfa2_info_gfapy_based.py
examples/gfa2_info/gfa2_stats_collector.py
examples/gfa2_info/invalid.gfa2
examples/gfa2_info/run_example.sh
py_bindings/.gitignore
py_bindings/py_bindings.nimble
py_bindings/src/py_bindings.nim
py_bindings/src/py_bindings.nim.cfg
tests/.gitignore
tests/conftest.py
tests/test_textformats_py.py
textformats/__init__.py
textformats/error.py
textformats/textformats.py
textformats.egg-info/PKG-INFO
textformats.egg-info/SOURCES.txt
textformats.egg-info/dependency_links.txt
textformats.egg-info/not-zip-safe
textformats.egg-info/top_level.txt