Metadata-Version: 2.1
Name: textformats
Version: 1.2.2
Summary: Simple definition and parsing of text formats
Home-page: https://github.com/ggonnella/textformats
Author: Giorgio Gonnella
Author-email: gonnella@zbh.uni-hamburg.de
License: ISC
Keywords: text,textformats,formats,fileformats,bioinformatics,genomics,sequences,science
Platform: UNKNOWN
Classifier: Development Status :: 5 - Production/Stable
Classifier: Environment :: Console
Classifier: Intended Audience :: Developers
Classifier: Intended Audience :: Science/Research
Classifier: License :: OSI Approved :: ISC License (ISCL)
Classifier: Operating System :: POSIX :: Linux
Classifier: Programming Language :: Python :: 3 :: Only
Classifier: Topic :: Software Development :: Libraries
